<annotation verified="yes">
    <folder>Annotation</folder>
    <filename>0617.jpg</filename>
    <path>PascalVoc/Annotations/0617.jpg</path>
    <source>
        <database>Unknown</database>
    </source>
    <size>
        <width>1280</width>
        <height>720</height>
        <depth>3</depth>
    </size>
    <segmented>0</segmented>
    <object>
    <name>zec</name>
    <pose>Unspecified</pose>
    <truncated>0</truncated>
    <difficult>0</difficult>
    <bndbox>
        <xmin>242.42424242424244</xmin>
        <ymin>37.57575757575758</ymin>
        <xmax>461.81818181818187</xmax>
        <ymax>680.0000000000001</ymax>
    </bndbox>
</object><object>
    <name>coke</name>
    <pose>Unspecified</pose>
    <truncated>0</truncated>
    <difficult>0</difficult>
    <bndbox>
        <xmin>427.8787878787879</xmin>
        <ymin>72.72727272727273</ymin>
        <xmax>561.2121212121212</xmax>
        <ymax>426.6666666666667</ymax>
    </bndbox>
</object><object>
    <name>couque_white</name>
    <pose>Unspecified</pose>
    <truncated>0</truncated>
    <difficult>0</difficult>
    <bndbox>
        <xmin>575.7575757575758</xmin>
        <ymin>103.03030303030303</ymin>
        <xmax>958.7878787878788</xmax>
        <ymax>367.27272727272725</ymax>
    </bndbox>
</object><object>
    <name>juicyfresh</name>
    <pose>Unspecified</pose>
    <truncated>0</truncated>
    <difficult>0</difficult>
    <bndbox>
        <xmin>574.5454545454546</xmin>
        <ymin>355.1515151515152</ymin>
        <xmax>778.1818181818182</xmax>
        <ymax>429.0909090909091</ymax>
    </bndbox>
</object><object>
    <name>vita500</name>
    <pose>Unspecified</pose>
    <truncated>0</truncated>
    <difficult>0</difficult>
    <bndbox>
        <xmin>944.2424242424242</xmin>
        <ymin>53.333333333333336</ymin>
        <xmax>1258.1818181818182</xmax>
        <ymax>383.030303030303</ymax>
    </bndbox>
</object><object>
    <name>chocopie</name>
    <pose>Unspecified</pose>
    <truncated>0</truncated>
    <difficult>0</difficult>
    <bndbox>
        <xmin>952.7272727272727</xmin>
        <ymin>441.21212121212125</ymin>
        <xmax>1187.878787878788</xmax>
        <ymax>720</ymax>
    </bndbox>
</object><object>
    <name>gumi_gumi</name>
    <pose>Unspecified</pose>
    <truncated>0</truncated>
    <difficult>0</difficult>
    <bndbox>
        <xmin>636.3636363636364</xmin>
        <ymin>420.6060606060606</ymin>
        <xmax>913.939393939394</xmax>
        <ymax>720</ymax>
    </bndbox>
</object><object>
    <name>tuna</name>
    <pose>Unspecified</pose>
    <truncated>0</truncated>
    <difficult>0</difficult>
    <bndbox>
        <xmin>459.39393939393943</xmin>
        <ymin>515.1515151515151</ymin>
        <xmax>615.7575757575758</xmax>
        <ymax>720</ymax>
    </bndbox>
</object>
</annotation>