<annotation verified="yes">
    <folder>Annotation</folder>
    <filename>0720.jpg</filename>
    <path>PascalVoc/Annotations/0720.jpg</path>
    <source>
        <database>Unknown</database>
    </source>
    <size>
        <width>1280</width>
        <height>720</height>
        <depth>3</depth>
    </size>
    <segmented>0</segmented>
    <object>
    <name>couque_white</name>
    <pose>Unspecified</pose>
    <truncated>0</truncated>
    <difficult>0</difficult>
    <bndbox>
        <xmin>136.88385269121812</xmin>
        <ymin>0</ymin>
        <xmax>533.0311614730879</xmax>
        <ymax>280.31486146095716</ymax>
    </bndbox>
</object><object>
    <name>zec</name>
    <pose>Unspecified</pose>
    <truncated>0</truncated>
    <difficult>0</difficult>
    <bndbox>
        <xmin>550.2549575070822</xmin>
        <ymin>0</ymin>
        <xmax>1221.0764872521247</xmax>
        <ymax>197.79596977329973</ymax>
    </bndbox>
</object><object>
    <name>coke</name>
    <pose>Unspecified</pose>
    <truncated>0</truncated>
    <difficult>0</difficult>
    <bndbox>
        <xmin>813.14447592068</xmin>
        <ymin>147.01511335012594</ymin>
        <xmax>1036.1473087818697</xmax>
        <ymax>322.9345088161209</ymax>
    </bndbox>
</object><object>
    <name>couque_coffee</name>
    <pose>Unspecified</pose>
    <truncated>0</truncated>
    <difficult>0</difficult>
    <bndbox>
        <xmin>806.7988668555241</xmin>
        <ymin>301.1712846347607</ymin>
        <xmax>1109.5750708215298</xmax>
        <ymax>684.7481108312343</ymax>
    </bndbox>
</object><object>
    <name>squid_peanut</name>
    <pose>Unspecified</pose>
    <truncated>0</truncated>
    <difficult>0</difficult>
    <bndbox>
        <xmin>488.6118980169972</xmin>
        <ymin>209.58438287153652</ymin>
        <xmax>844.872521246459</xmax>
        <ymax>718.2997481108312</ymax>
    </bndbox>
</object><object>
    <name>chocopie</name>
    <pose>Unspecified</pose>
    <truncated>0</truncated>
    <difficult>0</difficult>
    <bndbox>
        <xmin>271.95467422096317</xmin>
        <ymin>333.816120906801</ymin>
        <xmax>509.46175637393765</xmax>
        <ymax>614.9244332493703</ymax>
    </bndbox>
</object><object>
    <name>coke</name>
    <pose>Unspecified</pose>
    <truncated>0</truncated>
    <difficult>0</difficult>
    <bndbox>
        <xmin>197.62039660056658</xmin>
        <ymin>291.19647355163727</ymin>
        <xmax>359.8866855524079</xmax>
        <ymax>634.874055415617</ymax>
    </bndbox>
</object>
</annotation>